{"version":1,"resource":"vscode-remote://ssh-remote%2B71.64.199.65/home/blackjack/src/Blackjack/customThread.py","entries":[{"id":"FHT3.py","source":"renamed.source","sourceDescription":"~/src/Blackjack/customThread","timestamp":1729652076930},{"id":"t3m1.py","timestamp":1729652863890},{"id":"M4Ao.py","timestamp":1729653409735},{"id":"D8g3.py","timestamp":1729653444074},{"id":"mkBP.py","timestamp":1729653708522},{"id":"xwJV.py","source":"undoRedo.source","timestamp":1729653730102},{"id":"OCTN.py","timestamp":1729653832441},{"id":"KF8S.py","timestamp":1729654010580},{"id":"BJK2.py","timestamp":1729654178939},{"id":"dzHF.py","timestamp":1729654198769},{"id":"RHXK.py","timestamp":1729654212859},{"id":"GDN1.py","timestamp":1729654259778},{"id":"kuNn.py","timestamp":1729654411718},{"id":"ffjO.py","timestamp":1729654517467},{"id":"DV7K.py","timestamp":1729654539117},{"id":"6oXR.py","timestamp":1729654853754},{"id":"qf7M.py","timestamp":1729655111212},{"id":"RluJ.py","source":"undoRedo.source","timestamp":1729655133122},{"id":"jm3l.py","timestamp":1729655199972},{"id":"1oJz.py","timestamp":1729655273821},{"id":"1kzG.py","source":"undoRedo.source","timestamp":1729655295901},{"id":"fW0T.py","timestamp":1729655323061},{"id":"7ITi.py","timestamp":1729656136043},{"id":"4Cir.py","timestamp":1729656182012},{"id":"Yb9s.py","timestamp":1729656212482},{"id":"rOXj.py","source":"undoRedo.source","timestamp":1729656383120},{"id":"5HC5.py","timestamp":1729656608957},{"id":"OM5I.py","timestamp":1729656633617},{"id":"iWOe.py","timestamp":1729656693446},{"id":"S28Q.py","source":"undoRedo.source","timestamp":1729656734635},{"id":"xG51.py","timestamp":1729656949503},{"id":"uCwC.py","timestamp":1729656966513}]}